priomptipy/__init__.py
priomptipy/components.py
priomptipy/lib.py
priomptipy/openai_helper.py
priomptipy/output_cache.py
priomptipy/prompt_types.py
priomptipy/tokenizer.py
priomptipy-0.19.1.dist-info/METADATA
priomptipy-0.19.1.dist-info/WHEEL
priomptipy-0.19.1.dist-info/licenses/LICENSE
priomptipy-0.19.1.dist-info/RECORD
