Metadata-Version: 2.4
Name: priomptipy
Version: 0.19.1
Summary: A library for creating smarter prompts for LLMs by adding priority to components.
Project-URL: Homepage, https://github.com/tg1482/priomptipy
Project-URL: Repository, https://github.com/tg1482/priomptipy
Author-email: The Quarkle Dev Team <tanmay@quarkle.ai>
License: MIT License
License-File: LICENSE
Requires-Python: >=3.8
Requires-Dist: requests>=2.31.0
Requires-Dist: tiktoken>=0.7.0
Provides-Extra: dev
Requires-Dist: black>=23.0.0; extra == 'dev'
Requires-Dist: pytest-asyncio>=0.23.0; extra == 'dev'
Requires-Dist: pytest>=7.0.0; extra == 'dev'
